lmfit_varpro/__init__.py
lmfit_varpro/constraints.py
lmfit_varpro/qr_decomposition.py
lmfit_varpro/result.py
lmfit_varpro/separable_model.py
lmfit_varpro/util.py
tests/__init__.py
tests/test_helpers.py
tests/test_simple_kinetic_model.py
lmfit_varpro-0.0.5.post1.dist-info/AUTHORS.rst
lmfit_varpro-0.0.5.post1.dist-info/LICENSE
lmfit_varpro-0.0.5.post1.dist-info/METADATA
lmfit_varpro-0.0.5.post1.dist-info/WHEEL
lmfit_varpro-0.0.5.post1.dist-info/top_level.txt
lmfit_varpro-0.0.5.post1.dist-info/RECORD
