Metadata-Version: 2.1
Name: lmfit-varpro
Version: 0.0.5.post1
Summary: A variable projection implementation for Python/lmfit.
Home-page: https://github.com/glotaran/lmfit-varpro
Author: Joris Snellenburg, Joern Weissenborn
Author-email: j.snellenburg@gmail.com,
License: GPLv3
Download-URL: https://github.com/glotaran/lmfit-varpro/tarball/master
Keywords: alpha
Platform: UNKNOWN
Classifier: Development Status :: 2 - Pre-Alpha
Classifier: Intended Audience :: Science/Research
Classifier: Programming Language :: Python :: 3
Classifier: Programming Language :: Python :: 3.7
Classifier: Programming Language :: Python :: 3.8
Classifier: Programming Language :: Python :: 3.9
Classifier: License :: OSI Approved :: GNU General Public License v3 (GPLv3)
Classifier: Natural Language :: English
Classifier: Operating System :: OS Independent
Classifier: Topic :: Scientific/Engineering
Classifier: Topic :: Scientific/Engineering :: Physics
Classifier: Topic :: Scientific/Engineering :: Chemistry
Requires-Dist: numpy
Requires-Dist: lmfit
